mlmpy/__init__.py
mlmpy/base.py
mlmpy-0.0.9.5.dist-info/LICENCE
mlmpy-0.0.9.5.dist-info/METADATA
mlmpy-0.0.9.5.dist-info/WHEEL
mlmpy-0.0.9.5.dist-info/top_level.txt
mlmpy-0.0.9.5.dist-info/RECORD
