Metadata-Version: 2.1
Name: mlmpy
Version: 0.0.9.5
Summary: mlm python API
Home-page: https://github.com/polmonroig/mlm
Author: Pol Monroig
Author-email: polmonroig@gmail.com
License: UNKNOWN
Platform: UNKNOWN
Classifier: Programming Language :: Python :: 3
Classifier: License :: OSI Approved :: Apache Software License
Classifier: Operating System :: OS Independent
